reorder_editable/__init__.py
reorder_editable/__main__.py
reorder_editable/core.py
reorder_editable/py.typed
reorder_editable-0.1.3.dist-info/licenses/LICENSE
reorder_editable-0.1.3.dist-info/METADATA
reorder_editable-0.1.3.dist-info/WHEEL
reorder_editable-0.1.3.dist-info/entry_points.txt
reorder_editable-0.1.3.dist-info/top_level.txt
reorder_editable-0.1.3.dist-info/RECORD
