Metadata-Version: 2.4
Name: reorder_editable
Version: 0.1.3
Summary: a naive implementation to reorder .pth files for editable packages
Author: purarue
License-Expression: MIT
Project-URL: Homepage, https://github.com/purarue/reorder_editable
Keywords: packaging,pip
Classifier: Programming Language :: Python
Classifier: Programming Language :: Python :: 3
Classifier: Programming Language :: Python :: 3 :: Only
Classifier: Programming Language :: Python :: 3.10
Classifier: Programming Language :: Python :: 3.11
Classifier: Programming Language :: Python :: 3.12
Classifier: Programming Language :: Python :: 3.13
Requires-Python: >=3.10
License-File: LICENSE
Requires-Dist: click>=8.0
Provides-Extra: testing
Requires-Dist: flake8; extra == "testing"
Requires-Dist: mypy; extra == "testing"
Requires-Dist: pytest; extra == "testing"
Dynamic: license-file
